{
  "updatedAt": "2026-06-13T16:52:34.263Z",
  "connected": false,
  "hasNewData": false,
  "disconnectedReason": "no-newer-data",
  "records": [
    {
      "timestamp": "2026. 6. 12. 오전 10:04:42",
      "voltage": 3.264,
      "current": 17.7,
      "power": 0.058
    },
    {
      "timestamp": "2026. 6. 12. 오전 10:05:42",
      "voltage": 3.264,
      "current": 17.6,
      "power": 0.056
    },
    {
      "timestamp": "2026. 6. 12. 오전 10:06:41",
      "voltage": 3.26,
      "current": 17.8,
      "power": 0.058
    },
    {
      "timestamp": "2026. 6. 12. 오전 10:07:41",
      "voltage": 3.26,
      "current": 17.2,
      "power": 0.056
    },
    {
      "timestamp": "2026. 6. 12. 오전 10:08:41",
      "voltage": 3.26,
      "current": 17.6,
      "power": 0.058
    },
    {
      "timestamp": "2026. 6. 12. 오전 10:09:41",
      "voltage": 3.264,
      "current": 17.6,
      "power": 0.058
    },
    {
      "timestamp": "2026. 6. 12. 오전 10:10:41",
      "voltage": 3.26,
      "current": 17.5,
      "power": 0.056
    },
    {
      "timestamp": "2026. 6. 12. 오전 10:11:41",
      "voltage": 3.264,
      "current": 17.6,
      "power": 0.056
    },
    {
      "timestamp": "2026. 6. 12. 오전 10:12:42",
      "voltage": 3.26,
      "current": 17.4,
      "power": 0.056
    },
    {
      "timestamp": "2026. 6. 12. 오전 10:13:43",
      "voltage": 3.264,
      "current": 17.7,
      "power": 0.058
    },
    {
      "timestamp": "2026. 6. 12. 오전 10:14:42",
      "voltage": 3.26,
      "current": 17.6,
      "power": 0.058
    },
    {
      "timestamp": "2026. 6. 12. 오전 10:15:42",
      "voltage": 3.264,
      "current": 17.7,
      "power": 0.058
    },
    {
      "timestamp": "2026. 6. 12. 오전 10:16:42",
      "voltage": 3.264,
      "current": 17.6,
      "power": 0.058
    },
    {
      "timestamp": "2026. 6. 12. 오전 10:17:42",
      "voltage": 3.26,
      "current": 17.7,
      "power": 0.058
    },
    {
      "timestamp": "2026. 6. 12. 오전 10:18:45",
      "voltage": 3.264,
      "current": 17.6,
      "power": 0.058
    },
    {
      "timestamp": "2026. 6. 12. 오전 10:19:43",
      "voltage": 3.264,
      "current": 17.5,
      "power": 0.056
    },
    {
      "timestamp": "2026. 6. 12. 오전 10:20:43",
      "voltage": 3.264,
      "current": 17.9,
      "power": 0.058
    },
    {
      "timestamp": "2026. 6. 12. 오전 10:21:42",
      "voltage": 3.264,
      "current": 17.7,
      "power": 0.058
    },
    {
      "timestamp": "2026. 6. 12. 오전 10:22:43",
      "voltage": 3.26,
      "current": 17.4,
      "power": 0.056
    },
    {
      "timestamp": "2026. 6. 12. 오전 10:23:43",
      "voltage": 3.26,
      "current": 17.9,
      "power": 0.058
    },
    {
      "timestamp": "2026. 6. 12. 오전 10:24:43",
      "voltage": 3.26,
      "current": 17.6,
      "power": 0.058
    },
    {
      "timestamp": "2026. 6. 12. 오전 10:25:42",
      "voltage": 3.26,
      "current": 17.6,
      "power": 0.058
    },
    {
      "timestamp": "2026. 6. 12. 오전 10:26:43",
      "voltage": 3.264,
      "current": 17.4,
      "power": 0.056
    },
    {
      "timestamp": "2026. 6. 12. 오전 10:27:42",
      "voltage": 3.26,
      "current": 17.7,
      "power": 0.058
    },
    {
      "timestamp": "2026. 6. 12. 오전 10:28:42",
      "voltage": 3.26,
      "current": 17.6,
      "power": 0.058
    },
    {
      "timestamp": "2026. 6. 12. 오전 10:29:43",
      "voltage": 3.26,
      "current": 17.6,
      "power": 0.058
    },
    {
      "timestamp": "2026. 6. 12. 오전 10:30:46",
      "voltage": 3.264,
      "current": 17.6,
      "power": 0.058
    },
    {
      "timestamp": "2026. 6. 12. 오전 10:31:43",
      "voltage": 3.26,
      "current": 17.6,
      "power": 0.056
    },
    {
      "timestamp": "2026. 6. 12. 오전 10:32:46",
      "voltage": 3.264,
      "current": 17.7,
      "power": 0.058
    },
    {
      "timestamp": "2026. 6. 12. 오전 10:33:44",
      "voltage": 3.26,
      "current": 17.6,
      "power": 0.056
    },
    {
      "timestamp": "2026. 6. 12. 오전 10:34:43",
      "voltage": 3.26,
      "current": 17.6,
      "power": 0.058
    },
    {
      "timestamp": "2026. 6. 12. 오전 10:35:44",
      "voltage": 3.264,
      "current": 17.8,
      "power": 0.058
    },
    {
      "timestamp": "2026. 6. 12. 오전 10:36:48",
      "voltage": 3.26,
      "current": 17.9,
      "power": 0.058
    },
    {
      "timestamp": "2026. 6. 12. 오전 10:37:45",
      "voltage": 3.26,
      "current": 17.6,
      "power": 0.058
    },
    {
      "timestamp": "2026. 6. 12. 오전 10:38:44",
      "voltage": 3.264,
      "current": 17.5,
      "power": 0.056
    },
    {
      "timestamp": "2026. 6. 12. 오전 10:39:44",
      "voltage": 3.264,
      "current": 17.5,
      "power": 0.058
    },
    {
      "timestamp": "2026. 6. 12. 오전 10:40:46",
      "voltage": 3.26,
      "current": 17.7,
      "power": 0.056
    },
    {
      "timestamp": "2026. 6. 12. 오전 10:41:45",
      "voltage": 3.264,
      "current": 17.5,
      "power": 0.058
    },
    {
      "timestamp": "2026. 6. 12. 오전 10:42:47",
      "voltage": 3.26,
      "current": 17.7,
      "power": 0.056
    },
    {
      "timestamp": "2026. 6. 12. 오전 10:43:45",
      "voltage": 3.264,
      "current": 17.8,
      "power": 0.058
    },
    {
      "timestamp": "2026. 6. 12. 오전 10:44:44",
      "voltage": 3.264,
      "current": 17.6,
      "power": 0.058
    },
    {
      "timestamp": "2026. 6. 12. 오전 10:45:44",
      "voltage": 3.26,
      "current": 17.6,
      "power": 0.058
    },
    {
      "timestamp": "2026. 6. 12. 오전 10:46:44",
      "voltage": 3.26,
      "current": 17.6,
      "power": 0.058
    },
    {
      "timestamp": "2026. 6. 12. 오전 10:47:46",
      "voltage": 3.264,
      "current": 17.8,
      "power": 0.058
    },
    {
      "timestamp": "2026. 6. 12. 오전 10:48:47",
      "voltage": 3.26,
      "current": 17.6,
      "power": 0.058
    },
    {
      "timestamp": "2026. 6. 12. 오전 10:49:44",
      "voltage": 3.26,
      "current": 17.6,
      "power": 0.058
    },
    {
      "timestamp": "2026. 6. 12. 오전 10:50:49",
      "voltage": 3.26,
      "current": 17.6,
      "power": 0.058
    },
    {
      "timestamp": "2026. 6. 12. 오전 10:51:45",
      "voltage": 3.26,
      "current": 17.6,
      "power": 0.058
    },
    {
      "timestamp": "2026. 6. 12. 오전 10:52:46",
      "voltage": 3.26,
      "current": 17.6,
      "power": 0.058
    },
    {
      "timestamp": "2026. 6. 12. 오전 10:53:44",
      "voltage": 3.26,
      "current": 17.8,
      "power": 0.058
    },
    {
      "timestamp": "2026. 6. 12. 오전 10:54:44",
      "voltage": 3.26,
      "current": 17.7,
      "power": 0.058
    },
    {
      "timestamp": "2026. 6. 12. 오전 10:55:45",
      "voltage": 3.26,
      "current": 17.7,
      "power": 0.058
    },
    {
      "timestamp": "2026. 6. 12. 오전 10:56:45",
      "voltage": 3.26,
      "current": 17.6,
      "power": 0.058
    },
    {
      "timestamp": "2026. 6. 12. 오전 10:57:45",
      "voltage": 3.26,
      "current": 17.6,
      "power": 0.058
    },
    {
      "timestamp": "2026. 6. 12. 오전 10:58:46",
      "voltage": 3.26,
      "current": 17.8,
      "power": 0.058
    },
    {
      "timestamp": "2026. 6. 12. 오전 10:59:45",
      "voltage": 3.264,
      "current": 17.9,
      "power": 0.058
    },
    {
      "timestamp": "2026. 6. 12. 오전 11:00:45",
      "voltage": 3.264,
      "current": 17.6,
      "power": 0.058
    },
    {
      "timestamp": "2026. 6. 12. 오전 11:01:45",
      "voltage": 3.26,
      "current": 17.3,
      "power": 0.056
    },
    {
      "timestamp": "2026. 6. 12. 오전 11:02:45",
      "voltage": 3.26,
      "current": 17.6,
      "power": 0.058
    },
    {
      "timestamp": "2026. 6. 12. 오전 11:03:45",
      "voltage": 3.26,
      "current": 17.5,
      "power": 0.056
    },
    {
      "timestamp": "2026. 6. 12. 오전 11:04:44",
      "voltage": 3.264,
      "current": 17.7,
      "power": 0.058
    },
    {
      "timestamp": "2026. 6. 12. 오전 11:06:45",
      "voltage": 3.26,
      "current": 17.6,
      "power": 0.056
    },
    {
      "timestamp": "2026. 6. 12. 오전 11:07:51",
      "voltage": 3.26,
      "current": 17.7,
      "power": 0.058
    },
    {
      "timestamp": "2026. 6. 12. 오전 11:08:48",
      "voltage": 3.264,
      "current": 17.6,
      "power": 0.058
    },
    {
      "timestamp": "2026. 6. 12. 오전 11:09:48",
      "voltage": 3.26,
      "current": 17.8,
      "power": 0.058
    },
    {
      "timestamp": "2026. 6. 12. 오전 11:12:46",
      "voltage": 3.264,
      "current": 17.6,
      "power": 0.056
    },
    {
      "timestamp": "2026. 6. 12. 오전 11:13:49",
      "voltage": 3.26,
      "current": 17.7,
      "power": 0.058
    },
    {
      "timestamp": "2026. 6. 12. 오전 11:14:54",
      "voltage": 3.26,
      "current": 17.6,
      "power": 0.058
    },
    {
      "timestamp": "2026. 6. 12. 오전 11:15:49",
      "voltage": 3.26,
      "current": 17.3,
      "power": 0.058
    },
    {
      "timestamp": "2026. 6. 12. 오전 11:16:51",
      "voltage": 3.26,
      "current": 17.6,
      "power": 0.058
    },
    {
      "timestamp": "2026. 6. 12. 오전 11:20:49",
      "voltage": 3.26,
      "current": 17.5,
      "power": 0.058
    },
    {
      "timestamp": "2026. 6. 12. 오전 11:21:49",
      "voltage": 3.26,
      "current": 17.7,
      "power": 0.058
    },
    {
      "timestamp": "2026. 6. 12. 오전 11:22:50",
      "voltage": 3.26,
      "current": 17.8,
      "power": 0.058
    },
    {
      "timestamp": "2026. 6. 12. 오전 11:23:52",
      "voltage": 3.26,
      "current": 17.6,
      "power": 0.058
    },
    {
      "timestamp": "2026. 6. 12. 오전 11:24:54",
      "voltage": 3.26,
      "current": 17.7,
      "power": 0.058
    },
    {
      "timestamp": "2026. 6. 12. 오전 11:25:52",
      "voltage": 3.264,
      "current": 17.6,
      "power": 0.058
    },
    {
      "timestamp": "2026. 6. 12. 오전 11:26:50",
      "voltage": 3.26,
      "current": 17.8,
      "power": 0.058
    },
    {
      "timestamp": "2026. 6. 12. 오전 11:27:47",
      "voltage": 3.264,
      "current": 17.6,
      "power": 0.058
    },
    {
      "timestamp": "2026. 6. 12. 오전 11:29:04",
      "voltage": 3.26,
      "current": 17.6,
      "power": 0.058
    },
    {
      "timestamp": "2026. 6. 12. 오전 11:29:51",
      "voltage": 3.26,
      "current": 17.7,
      "power": 0.058
    },
    {
      "timestamp": "2026. 6. 12. 오전 11:31:52",
      "voltage": 3.26,
      "current": 17.6,
      "power": 0.058
    },
    {
      "timestamp": "2026. 6. 12. 오전 11:32:47",
      "voltage": 3.26,
      "current": 17.7,
      "power": 0.058
    }
  ]
}
